<?xml version="1.0" encoding="utf-8" ?>
<dwsync>
<file name="edit.php" server="h2806404.stratoserver.net//var/www/vhosts/shareyourmeal.nl/httpdocs/" local="131865075090000000" remote="131865075090000000" Dst="1" />
<file name="recipe_delete.php" server="h2806404.stratoserver.net//var/www/vhosts/shareyourmeal.nl/httpdocs/" local="131865020780000000" remote="131865020780000000" Dst="1" />
<file name="details_a.php" server="h2806404.stratoserver.net//var/www/vhosts/shareyourmeal.nl/httpdocs/" local="131863233730000000" remote="131863233730000000" Dst="1" />
<file name="details_admin.php" server="h2806404.stratoserver.net//var/www/vhosts/shareyourmeal.nl/httpdocs/" local="131865740580000000" remote="131865740580000000" Dst="1" />
<file name="edit_recipe.php" server="h2806404.stratoserver.net//var/www/vhosts/shareyourmeal.nl/httpdocs/" local="131864453490000000" remote="131864453490000000" Dst="1" />
<file name="details.php" server="h2806404.stratoserver.net//var/www/vhosts/shareyourmeal.nl/httpdocs/" local="131865734960000000" remote="131865734960000000" Dst="1" />
<file name="details.php" server="shareyourmeal.nl//var/www/vhosts/shareyourmeal.nl/httpdocs/" local="131865734960000000" remote="131868749540000000" Dst="1" />
<file name="details_a.php" server="shareyourmeal.nl//var/www/vhosts/shareyourmeal.nl/httpdocs/" local="131863233730000000" remote="131868749540000000" Dst="1" />
<file name="details_admin.php" server="shareyourmeal.nl//var/www/vhosts/shareyourmeal.nl/httpdocs/" local="131865740580000000" remote="131868749540000000" Dst="1" />
<file name="edit.php" server="shareyourmeal.nl//var/www/vhosts/shareyourmeal.nl/httpdocs/" local="131865075090000000" remote="131868749550000000" Dst="1" />
<file name="edit_recipe.php" server="shareyourmeal.nl//var/www/vhosts/shareyourmeal.nl/httpdocs/" local="131864453490000000" remote="131868749550000000" Dst="1" />
<file name="recipe_delete.php" server="shareyourmeal.nl//var/www/vhosts/shareyourmeal.nl/httpdocs/" local="131870057662155368" remote="131870057710000000" Dst="1" />
</dwsync>